red_commons/__init__.py
red_commons/logging/__init__.py
red_commons-1.0.0.dist-info/LICENSE
red_commons-1.0.0.dist-info/WHEEL
red_commons-1.0.0.dist-info/METADATA
red_commons-1.0.0.dist-info/RECORD
