Metadata-Version: 2.1
Name: Red-Commons
Version: 1.0.0
Summary: Common utilities used by multiple projects maintained by Cog Creators.
Author: Cog Creators
Requires-Python: >=3.8
Classifier: Development Status :: 5 - Production/Stable
Classifier: Intended Audience :: Developers
Classifier: License :: OSI Approved :: MIT License
Classifier: Operating System :: OS Independent
Classifier: Programming Language :: Python :: 3 :: Only
Classifier: Programming Language :: Python :: 3.8
Classifier: Programming Language :: Python :: 3.9
Classifier: Programming Language :: Python :: 3.10
Classifier: Programming Language :: Python :: 3.11
Requires-Dist: black==22.1.0 ; extra == "dev"
Requires-Dist: flake8==4.0.1 ; extra == "dev"
Requires-Dist: isort==5.10.1 ; extra == "dev"
Project-URL: Issue Tracker, https://github.com/Cog-Creators/Red-Commons/issues
Project-URL: Source Code, https://github.com/Cog-Creators/Red-Commons
Provides-Extra: dev
